{
	"posts": [{
			"id": 1,
			"title": "Hello World",
			"desc": "This is the first post on my blog",
			"date": "2022-01-01T00:00:00.000Z",
			"author": "John Doe"
		},
		{
			"id": 2,
			"title": "Angular for Beginners",
			"desc": "In this post, we will learn the basics of Angular",
			"date": "2022-01-02T00:00:00.000Z",
			"author": "Jane Doe"
		}, {
			"id": 3,
			"title": "Building a REST API",
			"desc": "Learn how to build a REST API using Node.js and Express",
			"date": "2022-01-03T00:00:00.000Z",
			"author": "John Doe"
		}, {
			"id": 4,
			"title": "Getting started with Firebase",
			"desc": "Learn how to use Firebase to build a real-time web app",
			"date": "2022-01-04T00:00:00.000Z",
			"author": "Jane Doe"
		}, {
			"id": 5,
			"title": "Creating a Single Page Application",
			"desc": "Learn how to create a single page application using Angular",
			"date": "2022-01-05T00:00:00.000Z",
			"author": "John Doe"
		},
		{
            "id": 6,
            "title": "The Benefits of Meditation",
            "desc": "Meditation has become increasingly popular in recent years, and for good reason. It has been shown to reduce stress, improve focus and mental clarity, and enhance overall well-being.",
            "date": "2023-01-26",
            "author": "John Doe"
        },
        {
            "id": 7,
            "title": "5 Delicious Vegetarian Recipes",
            "desc": "Looking for some new meal ideas? Try these 5 delicious vegetarian recipes, from roasted veggies to pasta dishes, you're sure to find something you'll love!",
            "date": "2023-01-26",
            "author": "Jane Doe"
        },
        {
            "id": 8,
            "title": "The Science of Sleep",
            "desc": "Getting enough sleep is crucial for our physical and mental health, yet many of us struggle with it. Learn about the science of sleep and how to improve the quality and quantity of your sleep.",
            "date": "2023-01-26",
            "author": "John Doe"
        },
        {
            "id": 9,
            "title": "The Art of Photography",
            "desc": "Photography is not just about taking pictures, it's an art form. Learn the basics of composition, lighting, and editing, and start capturing stunning images.",
            "date": "2023-01-26",
            "author": "Jane Doe"
        },
        {
            "id": 10,
            "title": "Healthy Eating on a Budget",
            "desc": "Eating healthy can be expensive, but it doesn't have to be. Learn some tips and tricks for sticking to a healthy diet while keeping your grocery budget in check.",
            "date": "2023-01-26",
            "author": "John Doe"
        },
        {
            "id": 11,
            "title": "The Best Workout Routines for Beginners",
            "desc": "Starting a new workout routine can be intimidating, but it doesn't have to be. Check out these beginner-friendly workout routines that will help you get started on your fitness journey.",
            "date": "2023-01-26",
            "author": "Jane Doe"
        },
        {
            "id": 12,
            "title": "How to Build a Successful Career",
            "desc": "Building a successful career takes hard work and dedication, but it's not impossible. Learn some tips and strategies for advancing your career and reaching your professional goals.",
            "date": "2023-01-26",
            "author": "John Doe"
        },
        {
            "id": 13,
            "title": "The Benefits of Gardening",
            "desc": "Gardening is more than just a hobby, it's a way to connect with nature and improve your well-being. Learn about the benefits of gardening, from reducing stress to increasing physical activity.",
            "date": "2023-01-26",
            "author": "Jane Doe"
        },
		{
            "id": 14,
            "title": "lorem ipsum",
            "desc": "lorem ipsum lorem ipsum lorem ipsum lorem ipsum",
            "date": "2023-01-26",
            "author": "Jane Doe"
        },
        {
			"id": 15,
			"title": "Creating a Single Page Application",
			"desc": "Learn how to create a single page application using Angular",
			"date": "2022-01-05T00:00:00.000Z",
			"author": "John Doe"
		},
        {
			"id": 16,
			"title": "Creating a Single Page Application",
			"desc": "Learn how to create a single page application using Angular",
			"date": "2022-01-05T00:00:00.000Z",
			"author": "John Doe"
		},
        {
			"id": 17,
			"title": "Creating a Single Page Application",
			"desc": "Learn how to create a single page application using Angular",
			"date": "2022-01-05T00:00:00.000Z",
			"author": "John Doe"
		},
        {
			"id": 18,
			"title": "Creating a Single Page Application",
			"desc": "Learn how to create a single page application using Angular",
			"date": "2022-01-05T00:00:00.000Z",
			"author": "John Doe"
		},
        {
			"id": 19,
			"title": "Creating a Single Page Application",
			"desc": "Learn how to create a single page application using Angular",
			"date": "2022-01-05T00:00:00.000Z",
			"author": "John Doe"
		},
        {
			"id": 20,
			"title": "Creating a Single Page Application",
			"desc": "Learn how to create a single page application using Angular",
			"date": "2022-01-05T00:00:00.000Z",
			"author": "John Doe"
		},
        {
			"id": 21,
			"title": "Creating a Single Page Application",
			"desc": "Learn how to create a single page application using Angular",
			"date": "2022-01-05T00:00:00.000Z",
			"author": "John Doe"
		},
        {
			"id": 22,
			"title": "Creating a Single Page Application",
			"desc": "Learn how to create a single page application using Angular",
			"date": "2022-01-05T00:00:00.000Z",
			"author": "John Doe"
		},
        {
			"id": 23,
			"title": "Creating a Single Page Application",
			"desc": "Learn how to create a single page application using Angular",
			"date": "2022-01-05T00:00:00.000Z",
			"author": "John Doe"
		},
        {
			"id": 24,
			"title": "Creating a Single Page Application",
			"desc": "Learn how to create a single page application using Angular",
			"date": "2022-01-05T00:00:00.000Z",
			"author": "John Doe"
		},
        {
			"id": 25,
			"title": "Creating a Single Page Application",
			"desc": "Learn how to create a single page application using Angular",
			"date": "2022-01-05T00:00:00.000Z",
			"author": "John Doe"
		},
        {
			"id": 26,
			"title": "Creating a Single Page Application",
			"desc": "Learn how to create a single page application using Angular",
			"date": "2022-01-05T00:00:00.000Z",
			"author": "John Doe"
		},
        {
			"id": 27,
			"title": "Creating a Single Page Application",
			"desc": "Learn how to create a single page application using Angular",
			"date": "2022-01-05T00:00:00.000Z",
			"author": "John Doe"
		},
        {
			"id": 28,
			"title": "Creating a Single Page Application",
			"desc": "Learn how to create a single page application using Angular",
			"date": "2022-01-05T00:00:00.000Z",
			"author": "John Doe"
		},
        {
			"id": 29,
			"title": "Creating a Single Page Application",
			"desc": "Learn how to create a single page application using Angular",
			"date": "2022-01-05T00:00:00.000Z",
			"author": "John Doe"
		},
        {
			"id": 30,
			"title": "Creating a Single Page Application",
			"desc": "Learn how to create a single page application using Angular",
			"date": "2022-01-05T00:00:00.000Z",
			"author": "John Doe"
		},
        {
			"id": 31,
			"title": "Creating a Single Page Application",
			"desc": "Learn how to create a single page application using Angular",
			"date": "2022-01-05T00:00:00.000Z",
			"author": "John Doe"
		},
        {
			"id": 32,
			"title": "Creating a Single Page Application",
			"desc": "Learn how to create a single page application using Angular",
			"date": "2022-01-05T00:00:00.000Z",
			"author": "John Doe"
		},
        {
			"id": 33,
			"title": "Creating a Single Page Application",
			"desc": "Learn how to create a single page application using Angular",
			"date": "2022-01-05T00:00:00.000Z",
			"author": "John Doe"
		},
        {
			"id": 34,
			"title": "Creating a Single Page Application",
			"desc": "Learn how to create a single page application using Angular",
			"date": "2022-01-05T00:00:00.000Z",
			"author": "John Doe"
		},
        {
			"id": 35,
			"title": "Creating a Single Page Application",
			"desc": "Learn how to create a single page application using Angular",
			"date": "2022-01-05T00:00:00.000Z",
			"author": "John Doe"
		},
		{
			"id": 36,
			"title": "Creating a Single Page Application",
			"desc": "Learn how to create a single page application using Angular",
			"date": "2022-01-05T00:00:00.000Z",
			"author": "John Doe"
		},
		{
			"id": 37,
			"title": "Creating a Single Page Application",
			"desc": "Learn how to create a single page application using Angular",
			"date": "2022-01-05T00:00:00.000Z",
			"author": "John Doe"
		},
		{
			"id": 38,
			"title": "Creating a Single Page Application",
			"desc": "Learn how to create a single page application using Angular",
			"date": "2022-01-05T00:00:00.000Z",
			"author": "John Doe"
		},
		{
			"id": 39,
			"title": "Creating a Single Page Application",
			"desc": "Learn how to create a single page application using Angular",
			"date": "2022-01-05T00:00:00.000Z",
			"author": "John Doe"
		},
		{
			"id": 40,
			"title": "Creating a Single Page Application",
			"desc": "Learn how to create a single page application using Angular",
			"date": "2022-01-05T00:00:00.000Z",
			"author": "John Doe"
		},
		{
			"id": 41,
			"title": "Creating a Single Page Application",
			"desc": "Learn how to create a single page application using Angular",
			"date": "2022-01-05T00:00:00.000Z",
			"author": "John Doe"
		},       
		{
			"id": 42,
			"title": "Creating a Single Page Application",
			"desc": "Learn how to create a single page application using Angular",
			"date": "2022-01-05T00:00:00.000Z",
			"author": "John Doe"
		},
		{
			"id": 43,
			"title": "Creating a Single Page Application",
			"desc": "Learn how to create a single page application using Angular",
			"date": "2022-01-05T00:00:00.000Z",
			"author": "John Doe"
		},
		{
			"id": 44,
			"title": "Creating a Single Page Application",
			"desc": "Learn how to create a single page application using Angular",
			"date": "2022-01-05T00:00:00.000Z",
			"author": "John Doe"
		},      
		 {
			"id": 45,
			"title": "Creating a Single Page Application",
			"desc": "Learn how to create a single page application using Angular",
			"date": "2022-01-05T00:00:00.000Z",
			"author": "John Doe"
		},
		{
			"id": 46,
			"title": "Creating a Single Page Application",
			"desc": "Learn how to create a single page application using Angular",
			"date": "2022-01-05T00:00:00.000Z",
			"author": "John Doe"
		},      
		 {
			"id": 47,
			"title": "Creating a Single Page Application",
			"desc": "Learn how to create a single page application using Angular",
			"date": "2022-01-05T00:00:00.000Z",
			"author": "John Doe"
		},
		{
			"id": 48,
			"title": "Creating a Single Page Application",
			"desc": "Learn how to create a single page application using Angular",
			"date": "2022-01-05T00:00:00.000Z",
			"author": "John Doe"
		},
		{
			"id": 49,
			"title": "Creating a Single Page Application",
			"desc": "Learn how to create a single page application using Angular",
			"date": "2022-01-05T00:00:00.000Z",
			"author": "John Doe"
		},
		{
			"id": 50,
			"title": "Creating a Single Page Application",
			"desc": "Learn how to create a single page application using Angular",
			"date": "2022-01-05T00:00:00.000Z",
			"author": "John Doe"
		},
		{
			"id": 51,
			"title": "Creating a Single Page Application",
			"desc": "Learn how to create a single page application using Angular",
			"date": "2022-01-05T00:00:00.000Z",
			"author": "John Doe"
		},
		{
			"id": 52,
			"title": "Creating a Single Page Application",
			"desc": "Learn how to create a single page application using Angular",
			"date": "2022-01-05T00:00:00.000Z",
			"author": "John Doe"
		}
	]
}